job_scraper/__init__.py
job_scraper/scraper.py
job_scraper_selenium-1.0.2.dist-info/licenses/LICENSE
job_scraper_selenium-1.0.2.dist-info/METADATA
job_scraper_selenium-1.0.2.dist-info/WHEEL
job_scraper_selenium-1.0.2.dist-info/top_level.txt
job_scraper_selenium-1.0.2.dist-info/RECORD
