Metadata-Version: 2.4
Name: job-scraper-selenium
Version: 1.0.2
Summary: A Python package for scraping job postings from Indeed and LinkedIn
Home-page: https://github.com/adilc0070/job-scraper
Author: Adil C
Author-email: adilc0070@gmail.com
Project-URL: Bug Reports, https://github.com/adilc0070/job-scraper/issues
Project-URL: Source, https://github.com/adilc0070/job-scraper
Keywords: job scraper indeed linkedin selenium web-scraping
Classifier: Development Status :: 4 - Beta
Classifier: Intended Audience :: Developers
Classifier: Topic :: Software Development :: Libraries :: Python Modules
Classifier: Topic :: Internet :: WWW/HTTP :: Dynamic Content
Classifier: License :: OSI Approved :: MIT License
Classifier: Programming Language :: Python :: 3
Classifier: Programming Language :: Python :: 3.7
Classifier: Programming Language :: Python :: 3.8
Classifier: Programming Language :: Python :: 3.9
Classifier: Programming Language :: Python :: 3.10
Classifier: Programming Language :: Python :: 3.11
Classifier: Programming Language :: Python :: 3.12
Classifier: Operating System :: OS Independent
Requires-Python: >=3.7
License-File: LICENSE
Requires-Dist: selenium>=4.0.0
Requires-Dist: beautifulsoup4>=4.9.0
Requires-Dist: webdriver-manager>=4.0.0
Dynamic: author
Dynamic: author-email
Dynamic: classifier
Dynamic: description
Dynamic: description-content-type
Dynamic: home-page
Dynamic: keywords
Dynamic: license-file
Dynamic: project-url
Dynamic: requires-dist
Dynamic: requires-python
Dynamic: summary
